facebook_graphql_scraper-1.1.2.dist-info/licenses/LICENSE
fb_graphql_scraper/__init__.py
fb_graphql_scraper/example.py
fb_graphql_scraper/facebook_graphql_scraper.py
fb_graphql_scraper/base/__init__.py
fb_graphql_scraper/base/base_page.py
fb_graphql_scraper/pages/__init__.py
fb_graphql_scraper/pages/page_optional.py
fb_graphql_scraper/tests/__init__.py
fb_graphql_scraper/utils/__init__.py
fb_graphql_scraper/utils/locator.py
fb_graphql_scraper/utils/parser.py
fb_graphql_scraper/utils/utils.py
facebook_graphql_scraper-1.1.2.dist-info/METADATA
facebook_graphql_scraper-1.1.2.dist-info/WHEEL
facebook_graphql_scraper-1.1.2.dist-info/top_level.txt
facebook_graphql_scraper-1.1.2.dist-info/RECORD
