Metadata-Version: 2.4
Name: facebook-graphql-scraper
Version: 1.1.2
Summary: Implement Facebook scraper for post data retrieval
Home-page: https://github.com/FaustRen/FB_graphql_scraper
Author: FaustRen
Author-email: faustren1z@gmail.com
License: MIT
Classifier: Programming Language :: Python :: 3.11
Classifier: License :: OSI Approved :: MIT License
Classifier: Operating System :: OS Independent
Requires-Python: >=3.11
License-File: LICENSE
Dynamic: author
Dynamic: author-email
Dynamic: classifier
Dynamic: description
Dynamic: description-content-type
Dynamic: home-page
Dynamic: license
Dynamic: license-file
Dynamic: requires-python
Dynamic: summary
